profet/__init__.py
profet/alphafold.py
profet/pdb.py
profet/profet.py
profet-0.0.1.dist-info/LICENSE
profet-0.0.1.dist-info/METADATA
profet-0.0.1.dist-info/WHEEL
profet-0.0.1.dist-info/top_level.txt
profet-0.0.1.dist-info/RECORD
