Metadata-Version: 2.1
Name: profet
Version: 0.0.1
Summary: Protein structure Fetcher from online databases
Home-page: https://github.com/alan-turing-institute/profet
Author: mooniean
Author-email: bcostagomes@turing.ac.uk
License: UNKNOWN
Project-URL: Bug Tracker, https://github.com/alan-turing-institute/profet/issues
Platform: UNKNOWN
Classifier: Programming Language :: Python :: 3
Classifier: License :: OSI Approved :: MIT License
Classifier: Operating System :: OS Independent
Requires-Python: >=3.8
License-File: LICENSE
Requires-Dist: numpy
Requires-Dist: pypdb
Requires-Dist: requests
Requires-Dist: pandas
Requires-Dist: requests-html
Requires-Dist: bs4
Provides-Extra: dev
Requires-Dist: pytest ; extra == 'dev'
